argdantic/__init__.py
argdantic/convert.py
argdantic/core.py
argdantic/fields.py
argdantic/py.typed
argdantic/registry.py
argdantic/testing.py
argdantic/utils.py
argdantic/version.py
argdantic/parsing/__init__.py
argdantic/parsing/actions.py
argdantic/parsing/arguments.py
argdantic/sources/__init__.py
argdantic/sources/base.py
argdantic/sources/dynamic.py
argdantic/sources/json.py
argdantic/sources/toml.py
argdantic/sources/yaml.py
argdantic/stores/__init__.py
argdantic/stores/base.py
argdantic/stores/json.py
argdantic/stores/toml.py
argdantic/stores/yaml.py
argdantic-1.3.3.dist-info/LICENSE
argdantic-1.3.3.dist-info/WHEEL
argdantic-1.3.3.dist-info/METADATA
argdantic-1.3.3.dist-info/RECORD
