Metadata-Version: 2.3
Name: argdantic
Version: 1.3.3
Summary: Typed command line interfaces with argparse and pydantic
Author-email: Edoardo Arnaudo <edoardo.arn@gmail.com>
Classifier: Development Status :: 4 - Beta
Classifier: Topic :: Software Development
Classifier: Operating System :: OS Independent
Classifier: Programming Language :: Python :: 3.8
Classifier: Programming Language :: Python :: 3.9
Classifier: Programming Language :: Python :: 3.10
Classifier: Programming Language :: Python :: 3.11
Classifier: Programming Language :: Python :: 3.12
Classifier: Typing :: Typed
Classifier: Intended Audience :: Information Technology
Classifier: Intended Audience :: Science/Research
Classifier: Intended Audience :: Developers
Classifier: License :: OSI Approved :: MIT License
Requires-Dist: pydantic >= 2.8.0, < 3.0
Requires-Dist: pydantic-settings >= 2.4.0, < 3
Requires-Dist: python-dotenv >= 1.0.0, < 2.0 ; extra == "all"
Requires-Dist: orjson >= 3.10.0, < 4.0 ; extra == "all"
Requires-Dist: toml >= 0.10.0, < 1.0 ; extra == "all"
Requires-Dist: tomli >= 2.0, < 3.0 ; extra == "all"
Requires-Dist: pyyaml >= 6.0.0, < 7.0 ; extra == "all"
Requires-Dist: tomli-w >= 1.0.0, < 2.0 ; extra == "all"
Requires-Dist: flit >= 3.9.0, < 4.0 ; extra == "dev"
Requires-Dist: ruff >= 0.5.6, < 1.0 ; extra == "dev"
Requires-Dist: mkdocs >= 1.6.0, < 2.0 ; extra == "docs"
Requires-Dist: mkdocs-material >= 9.5.0, < 10.0 ; extra == "docs"
Requires-Dist: mdx-include >= 1.4.0, < 2.0 ; extra == "docs"
Requires-Dist: python-dotenv >= 1.0.0, < 2.0 ; extra == "env"
Requires-Dist: orjson >= 3.10.0, < 4.0 ; extra == "json"
Requires-Dist: coverage >= 7.6.0, < 8.0 ; extra == "test"
Requires-Dist: mock >= 5.1.0, < 6.0 ; extra == "test"
Requires-Dist: pytest >= 8.3.0, < 9.0 ; extra == "test"
Requires-Dist: pytest-cov >= 5.0.0, < 6.0 ; extra == "test"
Requires-Dist: pytest-xdist >= 3.6.0, < 4.0 ; extra == "test"
Requires-Dist: toml >= 0.10.0, < 1.0 ; extra == "toml"
Requires-Dist: tomli >= 2.0, < 3.0 ; extra == "toml"
Requires-Dist: tomli-w >= 1.0.0, < 2.0 ; extra == "toml"
Requires-Dist: pyyaml >= 6.0.0, < 7.0 ; extra == "yaml"
Project-URL: Home, https://github.com/edornd
Provides-Extra: all
Provides-Extra: dev
Provides-Extra: docs
Provides-Extra: env
Provides-Extra: json
Provides-Extra: test
Provides-Extra: toml
Provides-Extra: yaml
